stadt_bonn_oparl/__init__.py
stadt_bonn_oparl/celery.py
stadt_bonn_oparl/chromadb_utils.py
stadt_bonn_oparl/config.py
stadt_bonn_oparl/download_service.py
stadt_bonn_oparl/enrichments.py
stadt_bonn_oparl/logging.py
stadt_bonn_oparl/models.py
stadt_bonn_oparl/oparl_fetcher.py
stadt_bonn_oparl/pdf_conversion_service.py
stadt_bonn_oparl/processors.py
stadt_bonn_oparl/reference_resolver.py
stadt_bonn_oparl/utils.py
stadt_bonn_oparl/agents/paper_classifier.py
stadt_bonn_oparl/agents/topic_scout.py
stadt_bonn_oparl/api/client.py
stadt_bonn_oparl/api/config.py
stadt_bonn_oparl/api/dependencies.py
stadt_bonn_oparl/api/metrics.py
stadt_bonn_oparl/api/models.py
stadt_bonn_oparl/api/server.py
stadt_bonn_oparl/api/helpers/__init__.py
stadt_bonn_oparl/api/helpers/consultations.py
stadt_bonn_oparl/api/helpers/helpers.py
stadt_bonn_oparl/api/helpers/meetings.py
stadt_bonn_oparl/api/helpers/memberships.py
stadt_bonn_oparl/api/helpers/persons.py
stadt_bonn_oparl/api/helpers/processors.py
stadt_bonn_oparl/api/routers/agendaitems.py
stadt_bonn_oparl/api/routers/bodies.py
stadt_bonn_oparl/api/routers/check_references.py
stadt_bonn_oparl/api/routers/consultations.py
stadt_bonn_oparl/api/routers/files.py
stadt_bonn_oparl/api/routers/locations.py
stadt_bonn_oparl/api/routers/meetings.py
stadt_bonn_oparl/api/routers/memberships.py
stadt_bonn_oparl/api/routers/organizations.py
stadt_bonn_oparl/api/routers/papers.py
stadt_bonn_oparl/api/routers/persons.py
stadt_bonn_oparl/api/routers/status.py
stadt_bonn_oparl/cli/__init__.py
stadt_bonn_oparl/cli/check_references.py
stadt_bonn_oparl/cli/consultation.py
stadt_bonn_oparl/cli/convert.py
stadt_bonn_oparl/cli/download.py
stadt_bonn_oparl/cli/enrich.py
stadt_bonn_oparl/cli/extract.py
stadt_bonn_oparl/cli/filter.py
stadt_bonn_oparl/cli/find.py
stadt_bonn_oparl/cli/helpers.py
stadt_bonn_oparl/cli/meeting.py
stadt_bonn_oparl/cli/research.py
stadt_bonn_oparl/cli/vectordb.py
stadt_bonn_oparl/mcp/server.py
stadt_bonn_oparl/papers/__init__.py
stadt_bonn_oparl-1.8.5.dist-info/METADATA
stadt_bonn_oparl-1.8.5.dist-info/WHEEL
stadt_bonn_oparl-1.8.5.dist-info/entry_points.txt
stadt_bonn_oparl-1.8.5.dist-info/licenses/LICENSE
stadt_bonn_oparl-1.8.5.dist-info/RECORD
