Metadata-Version: 2.4
Name: stadt-bonn-oparl
Version: 1.8.5
Summary: Work with OParl Papers (and it's related types).
Project-URL: Changelog, https://codeberg.org/machdenstaat/stadt-bonn-oparl/src/branch/main/CHANGELOG.md
Project-URL: Homepage, https://machdenstaat.de/
Project-URL: Issues, https://codeberg.org/machdenstaat/stadt-bonn-oparl/issues
Project-URL: Repository, https://codeberg.org/machdenstaat/stadt-bonn-oparl.git
Author-email: Christoph Görn <goern@machdenstaat.de>
License-Expression: GPL-3.0-or-later
License-File: LICENSE
Classifier: Development Status :: 5 - Production/Stable
Classifier: Environment :: Console
Classifier: Intended Audience :: Developers
Classifier: Operating System :: OS Independent
Classifier: Programming Language :: Python
Classifier: Programming Language :: Python :: 3 :: Only
Classifier: Programming Language :: Python :: 3.12
Classifier: Programming Language :: Python :: 3.13
Requires-Python: >=3.12
Requires-Dist: beautifulsoup4>=4.13.4
Requires-Dist: celery>=5.5.3
Requires-Dist: chromadb>=1.0.9
Requires-Dist: cyclopts>=3.16.1
Requires-Dist: docling>=2.32.0
Requires-Dist: fastapi[standard]>=0.115.9
Requires-Dist: fastmcp>=2.4.0
Requires-Dist: feedparser>=6.0.11
Requires-Dist: hishel>=0.1.2
Requires-Dist: logfire[celery,fastapi,httpx,requests,system-metrics]>=3.16.0
Requires-Dist: loguru>=0.7.3
Requires-Dist: orjson>=3.10.18
Requires-Dist: posthog>=4.0.1
Requires-Dist: prometheus-fastapi-instrumentator>=7.1.0
Requires-Dist: pydantic-ai-slim[anthropic,mcp]>=0.2.4
Requires-Dist: pydantic-settings>=2.9.1
Requires-Dist: python-dotenv>=1.1.0
Requires-Dist: requests>=2.32.3
Requires-Dist: sqlalchemy>=2.0.41
Requires-Dist: stadt-bonn-oparl-api-client>=1.8.2
Requires-Dist: uvicorn>=0.34.2
